mcp_server_oxigraph/__init__.py
mcp_server_oxigraph/__main__.py
mcp_server_oxigraph/server.py
mcp_server_oxigraph/utils.py
mcp_server_oxigraph/core/__init__.py
mcp_server_oxigraph/core/config.py
mcp_server_oxigraph/core/format.py
mcp_server_oxigraph/core/rdf.py
mcp_server_oxigraph/core/sparql.py
mcp_server_oxigraph/core/store.py
mcp_server_oxigraph-0.1.0.dist-info/METADATA
mcp_server_oxigraph-0.1.0.dist-info/WHEEL
mcp_server_oxigraph-0.1.0.dist-info/entry_points.txt
mcp_server_oxigraph-0.1.0.dist-info/licenses/LICENSE
mcp_server_oxigraph-0.1.0.dist-info/RECORD
