Metadata-Version: 2.4
Name: mcp-server-oxigraph
Version: 0.1.0
Summary: MCP server for PyOxigraph
Project-URL: Homepage, https://github.com/identimoji/mcp-server-oxigraph
Project-URL: Bug Tracker, https://github.com/identimoji/mcp-server-oxigraph/issues
Author-email: Identimoji <help@identimoji.io>
License: MIT
License-File: LICENSE
Keywords: knowledge graph,mcp,oxigraph,rdf,sparql
Classifier: Development Status :: 3 - Alpha
Classifier: License :: OSI Approved :: MIT License
Classifier: Operating System :: OS Independent
Classifier: Programming Language :: Python :: 3
Classifier: Programming Language :: Python :: 3.10
Classifier: Programming Language :: Python :: 3.11
Classifier: Programming Language :: Python :: 3.12
Requires-Python: >=3.10
Requires-Dist: mcp[cli]>=1.0.0
Requires-Dist: pyoxigraph==0.4.9
